glm-0.4.4.data/purelib/glm/__init__.py
glm-0.4.4.data/purelib/glm/_glm.so
glm-0.4.4.dist-info/LICENSE
glm-0.4.4.dist-info/METADATA
glm-0.4.4.dist-info/WHEEL
glm-0.4.4.dist-info/top_level.txt
glm-0.4.4.dist-info/RECORD
