Metadata-Version: 2.1
Name: glm
Version: 0.4.4
Summary: glm Python library
Home-page: https://github.com/NREL/glm
Author: Dheepak Krishnamurthy
Author-email: me@kdheepak.com
License: UNKNOWN
Platform: UNKNOWN
Classifier: Development Status :: 5 - Production/Stable
Classifier: Intended Audience :: Developers
Classifier: Intended Audience :: Science/Research
Classifier: License :: OSI Approved :: MIT License
Classifier: Natural Language :: English
Classifier: Operating System :: OS Independent
Classifier: Programming Language :: Python :: 2
Classifier: Programming Language :: Python :: 3
Classifier: Topic :: Scientific/Engineering
Provides-Extra: docs
Requires-Dist: mkdocs ; extra == 'docs'
Requires-Dist: inari[mkdocs] ; extra == 'docs'
Requires-Dist: mkdocs-material ; extra == 'docs'
Requires-Dist: black ; extra == 'docs'
Requires-Dist: pygments ; extra == 'docs'
Requires-Dist: pymdown-extensions ; extra == 'docs'
Provides-Extra: tests
Requires-Dist: pytest ; extra == 'tests'
Requires-Dist: pytest-ordering ; extra == 'tests'
Requires-Dist: pytest-cov ; extra == 'tests'
